cdktf_cdktf_provider_gitlab/__init__.py
cdktf_cdktf_provider_gitlab/py.typed
cdktf_cdktf_provider_gitlab/_jsii/__init__.py
cdktf_cdktf_provider_gitlab/_jsii/provider-gitlab@15.5.0.jsii.tgz
cdktf_cdktf_provider_gitlab/application/__init__.py
cdktf_cdktf_provider_gitlab/application_appearance/__init__.py
cdktf_cdktf_provider_gitlab/application_settings/__init__.py
cdktf_cdktf_provider_gitlab/branch/__init__.py
cdktf_cdktf_provider_gitlab/branch_protection/__init__.py
cdktf_cdktf_provider_gitlab/cluster_agent/__init__.py
cdktf_cdktf_provider_gitlab/cluster_agent_token/__init__.py
cdktf_cdktf_provider_gitlab/compliance_framework/__init__.py
cdktf_cdktf_provider_gitlab/data_gitlab_application/__init__.py
cdktf_cdktf_provider_gitlab/data_gitlab_branch/__init__.py
cdktf_cdktf_provider_gitlab/data_gitlab_cluster_agent/__init__.py
cdktf_cdktf_provider_gitlab/data_gitlab_cluster_agents/__init__.py
cdktf_cdktf_provider_gitlab/data_gitlab_compliance_framework/__init__.py
cdktf_cdktf_provider_gitlab/data_gitlab_current_user/__init__.py
cdktf_cdktf_provider_gitlab/data_gitlab_group/__init__.py
cdktf_cdktf_provider_gitlab/data_gitlab_group_access_tokens/__init__.py
cdktf_cdktf_provider_gitlab/data_gitlab_group_billable_member_memberships/__init__.py
cdktf_cdktf_provider_gitlab/data_gitlab_group_hook/__init__.py
cdktf_cdktf_provider_gitlab/data_gitlab_group_hooks/__init__.py
cdktf_cdktf_provider_gitlab/data_gitlab_group_ids/__init__.py
cdktf_cdktf_provider_gitlab/data_gitlab_group_membership/__init__.py
cdktf_cdktf_provider_gitlab/data_gitlab_group_provisioned_users/__init__.py
cdktf_cdktf_provider_gitlab/data_gitlab_group_saml_links/__init__.py
cdktf_cdktf_provider_gitlab/data_gitlab_group_service_account/__init__.py
cdktf_cdktf_provider_gitlab/data_gitlab_group_subgroups/__init__.py
cdktf_cdktf_provider_gitlab/data_gitlab_group_variable/__init__.py
cdktf_cdktf_provider_gitlab/data_gitlab_group_variables/__init__.py
cdktf_cdktf_provider_gitlab/data_gitlab_groups/__init__.py
cdktf_cdktf_provider_gitlab-15.5.0.dist-info/LICENSE
cdktf_cdktf_provider_gitlab-15.5.0.dist-info/METADATA
cdktf_cdktf_provider_gitlab-15.5.0.dist-info/WHEEL
cdktf_cdktf_provider_gitlab-15.5.0.dist-info/top_level.txt
cdktf_cdktf_provider_gitlab-15.5.0.dist-info/RECORD
